<annotation>
	<folder>07_Protaetia_speciosa_jousselini</folder>
	<filename>Ceton_Protaetia_speciosa_jousseliniredsearch_orgichemaspeciosaj.jpg</filename>
	<path>C:\Users\Asus\Google Drive\ylisansbiyoloji\01CetoniinaeSubFamily\07_Protaetia_speciosa_jousselini\Ceton_Protaetia_speciosa_jousseliniredsearch_orgichemaspeciosaj.jpg</path>
	<source>
		<database>Unknown</database>
	</source>
	<size>
		<width>466</width>
		<height>383</height>
		<depth>3</depth>
	</size>
	<segmented>0</segmented>
	<object>
		<name>Protaetia_speciosa_jousselini</name>
		<pose>Unspecified</pose>
		<truncated>0</truncated>
		<difficult>0</difficult>
		<bndbox>
			<xmin>250</xmin>
			<ymin>6</ymin>
			<xmax>444</xmax>
			<ymax>173</ymax>
		</bndbox>
	</object>
	<object>
		<name>Protaetia_speciosa_jousselini</name>
		<pose>Unspecified</pose>
		<truncated>1</truncated>
		<difficult>0</difficult>
		<bndbox>
			<xmin>1</xmin>
			<ymin>39</ymin>
			<xmax>196</xmax>
			<ymax>377</ymax>
		</bndbox>
	</object>
	<object>
		<name>Protaetia_speciosa_jousselini</name>
		<pose>Unspecified</pose>
		<truncated>0</truncated>
		<difficult>0</difficult>
		<bndbox>
			<xmin>212</xmin>
			<ymin>189</ymin>
			<xmax>426</xmax>
			<ymax>373</ymax>
		</bndbox>
	</object>
</annotation>
