<annotation>
	<folder>train</folder>
	<filename>Ceton_Oxythyrea_funestabiolib_cz94260.jpg</filename>
	<path>C:\Users\Asus\Google Drive\ylisansbiyoloji\01Cetoniinae\06_Oxythyrea_funesta_yeniden\train\Ceton_Oxythyrea_funestabiolib_cz94260.jpg</path>
	<source>
		<database>Unknown</database>
	</source>
	<size>
		<width>560</width>
		<height>800</height>
		<depth>3</depth>
	</size>
	<segmented>0</segmented>
	<object>
		<name>06_Oxythyrea_funesta</name>
		<pose>Unspecified</pose>
		<truncated>0</truncated>
		<difficult>0</difficult>
		<bndbox>
			<xmin>169</xmin>
			<ymin>226</ymin>
			<xmax>449</xmax>
			<ymax>652</ymax>
		</bndbox>
	</object>
</annotation>
